nwmps/__init__.py
nwmps/gauges.py
nwmps/olmap.py
nwmps/reaches.py
nwmps/service.py
nwmps/utilities.py
nwm_plugins-0.0.4.dist-info/LICENSE
nwm_plugins-0.0.4.dist-info/METADATA
nwm_plugins-0.0.4.dist-info/WHEEL
nwm_plugins-0.0.4.dist-info/entry_points.txt
nwm_plugins-0.0.4.dist-info/top_level.txt
nwm_plugins-0.0.4.dist-info/RECORD
