Metadata-Version: 2.1
Name: nwm_plugins
Version: 0.0.4
Summary: Intake drivers for the National Water Model Post-Processing Services and API
Author-email: Aquaveo LLC <gromero@aquaveo.com>
License: The MIT License (MIT)
Project-URL: Homepage, https://github.com/FIRO-Tethys/nwmp_plugins
Project-URL: Issues, https://github.com/FIRO-Tethys/nwmp_plugins/issues
Classifier: License :: OSI Approved :: MIT License
Requires-Python: >=3.6
License-File: LICENSE
Requires-Dist: intake>=0.6.6
Requires-Dist: pandas
Requires-Dist: numpy
Requires-Dist: requests
Requires-Dist: shapely
Requires-Dist: pyproj
Requires-Dist: geopandas
Requires-Dist: pynhd
Requires-Dist: pygeoogc
Requires-Dist: pygeoutils
Requires-Dist: pygeohydro
Requires-Dist: geoalchemy2
Requires-Dist: httpx
Requires-Dist: asyncio
